qt_ledwidget/__init__.py
qt_ledwidget/example_app.py
qt_ledwidget/led_widget.py
qt_ledwidget/led_widget_res_rc.py
qt_ledwidget-0.2.dist-info/METADATA
qt_ledwidget-0.2.dist-info/RECORD
qt_ledwidget-0.2.dist-info/WHEEL
qt_ledwidget-0.2.dist-info/top_level.txt
